<?xml version="1.0" encoding="UTF-8"?>
<config>
    <acl>
        <resources>
            <admin>
                <children>
                    <system>
                        <children>
                            <config>
                                <children>
                                    <deleteorder translate="title" module="padoo_deleteorder">
                                        <title>Padoosoft delete order</title>
                                        <sort_order>10</sort_order>
                                    </deleteorder>
                                </children>
                            </config>
                        </children>
                    </system>
                </children>
            </admin>
        </resources>
    </acl>
 </config>